rest_framework_inclusions/__init__.py
rest_framework_inclusions/apps.py
rest_framework_inclusions/core.py
rest_framework_inclusions/renderer.py
testapp/__init__.py
testapp/loaders.py
testapp/models.py
testapp/renderers.py
testapp/serializers.py
testapp/settings.py
testapp/urls.py
testapp/viewsets.py
tests/__init__.py
tests/conftest.py
tests/mixins.py
tests/test_basic.py
tests/test_chained_loading.py
tests/test_references.py
djangorestframework_inclusions-1.2.0.dist-info/LICENSE
djangorestframework_inclusions-1.2.0.dist-info/METADATA
djangorestframework_inclusions-1.2.0.dist-info/WHEEL
djangorestframework_inclusions-1.2.0.dist-info/top_level.txt
djangorestframework_inclusions-1.2.0.dist-info/RECORD
